pragmail/__init__.py
pragmail/__version__.py
pragmail/clients.py
pragmail/exceptions.py
pragmail/py.typed
pragmail/transports.py
pragmail/utils.py
pragmail-0.2.5.dist-info/LICENSE
pragmail-0.2.5.dist-info/WHEEL
pragmail-0.2.5.dist-info/METADATA
pragmail-0.2.5.dist-info/RECORD
