Metadata-Version: 2.1
Name: pragmail
Version: 0.2.5
Summary: Simple library for retrieving and repackaging email messages.
License: MIT
Author: Hju Kneyck Flores
Author-email: hjucode@gmail.com
Requires-Python: >=3.9,<4.0
Classifier: License :: OSI Approved :: MIT License
Classifier: Programming Language :: Python :: 3
Classifier: Programming Language :: Python :: 3.10
Classifier: Programming Language :: Python :: 3.9
